jetblack_fixengine/__init__.py
jetblack_fixengine/acceptor/__init__.py
jetblack_fixengine/acceptor/acceptor.py
jetblack_fixengine/acceptor/helpers.py
jetblack_fixengine/acceptor/state_machine.py
jetblack_fixengine/acceptor/state_transitions.py
jetblack_fixengine/acceptor/types.py
jetblack_fixengine/admin/__init__.py
jetblack_fixengine/admin/state_processor.py
jetblack_fixengine/admin/state_transitions.py
jetblack_fixengine/admin/types.py
jetblack_fixengine/initiator/__init__.py
jetblack_fixengine/initiator/helpers.py
jetblack_fixengine/initiator/initiator.py
jetblack_fixengine/initiator/state_machine.py
jetblack_fixengine/initiator/state_transitions.py
jetblack_fixengine/initiator/types.py
jetblack_fixengine/managers/__init__.py
jetblack_fixengine/managers/initiator_manager.py
jetblack_fixengine/persistence/__init__.py
jetblack_fixengine/persistence/file_store.py
jetblack_fixengine/persistence/sql_store.py
jetblack_fixengine/py.typed
jetblack_fixengine/time_provider.py
jetblack_fixengine/transports/__init__.py
jetblack_fixengine/transports/fix_events.py
jetblack_fixengine/transports/fix_read_buffer.py
jetblack_fixengine/transports/fix_reader_async.py
jetblack_fixengine/transports/fix_transport.py
jetblack_fixengine/transports/state_machine.py
jetblack_fixengine/transports/state_processor.py
jetblack_fixengine/transports/state_transitions.py
jetblack_fixengine/transports/types.py
jetblack_fixengine/types.py
jetblack_fixengine/utils/__init__.py
jetblack_fixengine/utils/cancellation.py
jetblack_fixengine/utils/date_utils.py
jetblack_fixengine-1.0.0a5.dist-info/LICENSE
jetblack_fixengine-1.0.0a5.dist-info/WHEEL
jetblack_fixengine-1.0.0a5.dist-info/METADATA
jetblack_fixengine-1.0.0a5.dist-info/RECORD
